mercupy_parser/__init__.py
mercupy_parser-0.2.1.dist-info/LICENSE
mercupy_parser-0.2.1.dist-info/METADATA
mercupy_parser-0.2.1.dist-info/WHEEL
mercupy_parser-0.2.1.dist-info/top_level.txt
mercupy_parser-0.2.1.dist-info/RECORD
