Metadata-Version: 2.1
Name: mercupy-parser
Version: 0.2.1
Summary: Python wrapper for mercury-parser
Home-page: https://github.com/nikosNalmpantis/mercupy-parser
Author: Nikos Nalmpantis
Author-email: nikosnalmpantis@outlook.com
License: GNU General Public License v3.0
Platform: UNKNOWN
License-File: LICENSE
Requires-Dist: httpx
